kiskadee/__init__.py
kiskadee/dataLoader.py
kiskadee/kinetics.py
kiskadee/thermogravimetricAnalysis.py
kiskadee-0.0.4.dist-info/LICENSE
kiskadee-0.0.4.dist-info/METADATA
kiskadee-0.0.4.dist-info/WHEEL
kiskadee-0.0.4.dist-info/top_level.txt
kiskadee-0.0.4.dist-info/RECORD
