Metadata-Version: 2.1
Name: kiskadee
Version: 0.0.4
Summary: Kinetics Degradation Module
Home-page: https://github.com/matheusdepra/kiskadee
Download-URL: https://github.com/matheusdepra/kiskadee/archive/refs/tags/0.0.4.tar.gz
Author: Matheus de Prá Andrade
Author-email: mpandrade@ucs.br
License: MIT
Keywords: kiskadee,fwo
Classifier: Development Status :: 3 - Alpha
Classifier: Intended Audience :: Developers
Classifier: Topic :: Software Development :: Build Tools
Classifier: License :: OSI Approved :: MIT License
Classifier: Programming Language :: Python :: 3.7
Classifier: Programming Language :: Python :: 3.8
Classifier: Programming Language :: Python :: 3.9
Classifier: Programming Language :: Python :: 3.10
Classifier: Programming Language :: Python :: 3.11
Classifier: Programming Language :: Python :: 3.12
License-File: LICENSE
